AUTHORS.rst
CONTRIBUTING.rst
HISTORY.rst
LICENSE
MANIFEST.in
README.md
pyproject.toml
setup.cfg
src/redshift_tools/__init__.py
src/redshift_tools/base.py
src/redshift_tools/catalog.py
src/redshift_tools/create.py
src/redshift_tools/manipulate.py
src/redshift_tools/plot.py
src/redshift_tools.egg-info/PKG-INFO
src/redshift_tools.egg-info/SOURCES.txt
src/redshift_tools.egg-info/dependency_links.txt
src/redshift_tools.egg-info/not-zip-safe
src/redshift_tools.egg-info/requires.txt
src/redshift_tools.egg-info/top_level.txt
tests/test_redshift_tools.py