Metadata-Version: 2.1
Name: redshift_tools
Version: 0.3.0
Summary: Package to create and mmanipulate redshift distributions for cosmic shear forecasts or analyses
Author: Silvan Fischbacher
Author-email: silvanf@phys.ethz.ch
License: MIT License
Project-URL: Source, https://cosmo-docs.phys.ethz.ch/redshift_tools
Classifier: Intended Audience :: Science/Research
Classifier: Intended Audience :: Developers
Classifier: License :: OSI Approved :: MIT License
Classifier: Natural Language :: English
Classifier: Programming Language :: Python :: 3
Classifier: Programming Language :: Python :: 3.9
Classifier: Programming Language :: Python :: 3.10
Classifier: Operating System :: OS Independent
Requires-Python: >=3.7
License-File: LICENSE
License-File: AUTHORS.rst
Requires-Dist: numpy
Requires-Dist: matplotlib
Requires-Dist: cycler
Requires-Dist: scipy
Requires-Dist: PyCosmo
Requires-Dist: astropy
Requires-Dist: cosmic_toolbox
Provides-Extra: dev
Requires-Dist: twine; extra == "dev"
Requires-Dist: pytest<7.2.0; extra == "dev"
Requires-Dist: pytest-cov; extra == "dev"
Requires-Dist: pytest-regtest; extra == "dev"
Requires-Dist: tox; extra == "dev"
Requires-Dist: flake8; extra == "dev"
Requires-Dist: black; extra == "dev"
Requires-Dist: isort; extra == "dev"
Requires-Dist: sphinx; extra == "dev"
Requires-Dist: sphinx-pynpoint-theme; extra == "dev"
Requires-Dist: myst-parser; extra == "dev"
Provides-Extra: docs
Requires-Dist: sphinx<7; extra == "docs"
Requires-Dist: sphinx-pynpoint-theme; extra == "docs"
Requires-Dist: myst-parser; extra == "docs"
